[
  {
    "number":0,
    "value":7774.1132908341,
    "datetime_start":1742221719811,
    "datetime_complete":1742221895600,
    "duration":175789,
    "params_accepted_score":1,
    "params_cooling_function":"exponential",
    "params_final_temp":46.4664781552,
    "params_global_best_score":16,
    "params_init_temp":1000,
    "params_iterations":2000,
    "params_local_best_score":4,
    "state":"COMPLETE",
    "problem_instance":"C101.txt"
  },
  {
    "number":1,
    "value":7687.0508365319,
    "datetime_start":1742221895600,
    "datetime_complete":1742222069879,
    "duration":174279,
    "params_accepted_score":6,
    "params_cooling_function":"linear",
    "params_final_temp":0.2183875355,
    "params_global_best_score":20,
    "params_init_temp":1100,
    "params_iterations":2000,
    "params_local_best_score":16,
    "state":"COMPLETE",
    "problem_instance":"C101.txt"
  },
  {
    "number":2,
    "value":7893.8283204818,
    "datetime_start":1742222069879,
    "datetime_complete":1742222411216,
    "duration":341336,
    "params_accepted_score":4,
    "params_cooling_function":"exponential",
    "params_final_temp":56.2135300108,
    "params_global_best_score":20,
    "params_init_temp":2000,
    "params_iterations":4000,
    "params_local_best_score":5,
    "state":"COMPLETE",
    "problem_instance":"C101.txt"
  },
  {
    "number":3,
    "value":7651.8972860156,
    "datetime_start":1742222411216,
    "datetime_complete":1742222661156,
    "duration":249940,
    "params_accepted_score":3,
    "params_cooling_function":"exponential",
    "params_final_temp":41.4520347066,
    "params_global_best_score":20,
    "params_init_temp":1000,
    "params_iterations":3000,
    "params_local_best_score":4,
    "state":"COMPLETE",
    "problem_instance":"C101.txt"
  },
  {
    "number":4,
    "value":8122.068859325,
    "datetime_start":1742222661156,
    "datetime_complete":1742222740270,
    "duration":79113,
    "params_accepted_score":3,
    "params_cooling_function":"linear",
    "params_final_temp":0.725310399,
    "params_global_best_score":18,
    "params_init_temp":600,
    "params_iterations":1000,
    "params_local_best_score":4,
    "state":"COMPLETE",
    "problem_instance":"C101.txt"
  },
  {
    "number":5,
    "value":7845.5640579655,
    "datetime_start":1742222740271,
    "datetime_complete":1742223174856,
    "duration":434585,
    "params_accepted_score":2,
    "params_cooling_function":"linear",
    "params_final_temp":0.336300821,
    "params_global_best_score":6,
    "params_init_temp":100,
    "params_iterations":5000,
    "params_local_best_score":3,
    "state":"COMPLETE",
    "problem_instance":"C101.txt"
  },
  {
    "number":6,
    "value":7863.0268744046,
    "datetime_start":1742223174857,
    "datetime_complete":1742223699785,
    "duration":524927,
    "params_accepted_score":8,
    "params_cooling_function":"linear",
    "params_final_temp":0.2224842492,
    "params_global_best_score":16,
    "params_init_temp":100,
    "params_iterations":6000,
    "params_local_best_score":13,
    "state":"COMPLETE",
    "problem_instance":"C101.txt"
  },
  {
    "number":7,
    "value":7789.3178316229,
    "datetime_start":1742223699786,
    "datetime_complete":1742223874925,
    "duration":175139,
    "params_accepted_score":1,
    "params_cooling_function":"exponential",
    "params_final_temp":27.5969164088,
    "params_global_best_score":7,
    "params_init_temp":2000,
    "params_iterations":2000,
    "params_local_best_score":4,
    "state":"COMPLETE",
    "problem_instance":"C101.txt"
  },
  {
    "number":8,
    "value":7891.9740570459,
    "datetime_start":1742223874926,
    "datetime_complete":1742224233041,
    "duration":358115,
    "params_accepted_score":1,
    "params_cooling_function":"exponential",
    "params_final_temp":77.8922536396,
    "params_global_best_score":8,
    "params_init_temp":3000,
    "params_iterations":4000,
    "params_local_best_score":3,
    "state":"COMPLETE",
    "problem_instance":"C101.txt"
  },
  {
    "number":9,
    "value":7737.5478378771,
    "datetime_start":1742224233042,
    "datetime_complete":1742224768710,
    "duration":535667,
    "params_accepted_score":1,
    "params_cooling_function":"exponential",
    "params_final_temp":46.3651241653,
    "params_global_best_score":11,
    "params_init_temp":3000,
    "params_iterations":6000,
    "params_local_best_score":3,
    "state":"COMPLETE",
    "problem_instance":"C101.txt"
  },
  {
    "number":10,
    "value":7903.5054041801,
    "datetime_start":1742224768710,
    "datetime_complete":1742225467286,
    "duration":698575,
    "params_accepted_score":4,
    "params_cooling_function":"exponential",
    "params_final_temp":92.6572496402,
    "params_global_best_score":13,
    "params_init_temp":2000,
    "params_iterations":8000,
    "params_local_best_score":7,
    "state":"COMPLETE",
    "problem_instance":"C101.txt"
  },
  {
    "number":11,
    "value":7715.126374172,
    "datetime_start":1742225467287,
    "datetime_complete":1742225720397,
    "duration":253110,
    "params_accepted_score":17,
    "params_cooling_function":"linear",
    "params_final_temp":0.0731312313,
    "params_global_best_score":20,
    "params_init_temp":600,
    "params_iterations":3000,
    "params_local_best_score":18,
    "state":"COMPLETE",
    "problem_instance":"C101.txt"
  },
  {
    "number":12,
    "value":7962.9522527241,
    "datetime_start":1742225720398,
    "datetime_complete":1742225803681,
    "duration":83282,
    "params_accepted_score":7,
    "params_cooling_function":"linear",
    "params_final_temp":0.6200263893,
    "params_global_best_score":17,
    "params_init_temp":1100,
    "params_iterations":1000,
    "params_local_best_score":11,
    "state":"COMPLETE",
    "problem_instance":"C101.txt"
  },
  {
    "number":13,
    "value":7955.9576442166,
    "datetime_start":1742225803682,
    "datetime_complete":1742226054139,
    "duration":250456,
    "params_accepted_score":6,
    "params_cooling_function":"linear",
    "params_final_temp":0.8273514761,
    "params_global_best_score":13,
    "params_init_temp":1100,
    "params_iterations":3000,
    "params_local_best_score":8,
    "state":"COMPLETE",
    "problem_instance":"C101.txt"
  },
  {
    "number":14,
    "value":7891.8063608584,
    "datetime_start":1742226054139,
    "datetime_complete":1742226316709,
    "duration":262569,
    "params_accepted_score":11,
    "params_cooling_function":"exponential",
    "params_final_temp":22.101263365,
    "params_global_best_score":20,
    "params_init_temp":2000,
    "params_iterations":3000,
    "params_local_best_score":18,
    "state":"COMPLETE",
    "problem_instance":"C101.txt"
  },
  {
    "number":15,
    "value":8115.4631860224,
    "datetime_start":1742226316710,
    "datetime_complete":1742226490193,
    "duration":173482,
    "params_accepted_score":5,
    "params_cooling_function":"linear",
    "params_final_temp":0.3948971539,
    "params_global_best_score":15,
    "params_init_temp":600,
    "params_iterations":2000,
    "params_local_best_score":11,
    "state":"COMPLETE",
    "problem_instance":"C101.txt"
  },
  {
    "number":16,
    "value":7966.5112432904,
    "datetime_start":1742226490194,
    "datetime_complete":1742226921959,
    "duration":431765,
    "params_accepted_score":9,
    "params_cooling_function":"linear",
    "params_final_temp":0.1004967037,
    "params_global_best_score":18,
    "params_init_temp":600,
    "params_iterations":5000,
    "params_local_best_score":15,
    "state":"COMPLETE",
    "problem_instance":"C101.txt"
  },
  {
    "number":17,
    "value":7888.2120276837,
    "datetime_start":1742226921959,
    "datetime_complete":1742227006551,
    "duration":84591,
    "params_accepted_score":3,
    "params_cooling_function":"exponential",
    "params_final_temp":25.1684423771,
    "params_global_best_score":10,
    "params_init_temp":2000,
    "params_iterations":1000,
    "params_local_best_score":6,
    "state":"COMPLETE",
    "problem_instance":"C101.txt"
  },
  {
    "number":18,
    "value":7743.8380450623,
    "datetime_start":1742227006551,
    "datetime_complete":1742227719854,
    "duration":713302,
    "params_accepted_score":5,
    "params_cooling_function":"exponential",
    "params_final_temp":62.9473359634,
    "params_global_best_score":14,
    "params_init_temp":3000,
    "params_iterations":8000,
    "params_local_best_score":9,
    "state":"COMPLETE",
    "problem_instance":"C101.txt"
  }
]